{
  "height": 7,
  "img": "7VW.png",
  "desc": "7 height, single stroke, variable width",
  "advance": 1,
  "glyphs": [
    {
      "char": "A",
      "x": 0,
      "y": 0,
      "w": 4
    },
    {
      "char": "B",
      "x": 5,
      "y": 0,
      "w": 4
    },
    {
      "char": "C",
      "x": 11,
      "y": 0,
      "w": 4
    },
    {
      "char": "D",
      "x": 16,
      "y": 0,
      "w": 4
    },
    {
      "char": "E",
      "x": 21,
      "y": 0,
      "w": 4
    },
    {
      "char": "F",
      "x": 26,
      "y": 0,
      "w": 4
    },
    {
      "char": "G",
      "x": 31,
      "y": 0,
      "w": 4
    },
    {
      "char": "H",
      "x": 36,
      "y": 0,
      "w": 4
    },
    {
      "char": "I",
      "x": 41,
      "y": 0,
      "w": 3
    },
    {
      "char": "J",
      "x": 45,
      "y": 0,
      "w": 4
    },
    {
      "char": "K",
      "x": 50,
      "y": 0,
      "w": 4
    },
    {
      "char": "L",
      "x": 55,
      "y": 0,
      "w": 4
    },
    {
      "char": "M",
      "x": 60,
      "y": 0,
      "w": 5
    },
    {
      "char": "N",
      "x": 66,
      "y": 0,
      "w": 5
    },
    {
      "char": "O",
      "x": 72,
      "y": 0,
      "w": 4
    },
    {
      "char": "P",
      "x": 77,
      "y": 0,
      "w": 4
    },
    {
      "char": "Q",
      "x": 82,
      "y": 0,
      "w": 4
    },
    {
      "char": "R",
      "x": 87,
      "y": 0,
      "w": 4
    },
    {
      "char": "S",
      "x": 92,
      "y": 0,
      "w": 4
    },
    {
      "char": "T",
      "x": 97,
      "y": 0,
      "w": 3
    },
    {
      "char": "U",
      "x": 101,
      "y": 0,
      "w": 4
    },
    {
      "char": "V",
      "x": 106,
      "y": 0,
      "w": 5
    },
    {
      "char": "W",
      "x": 112,
      "y": 0,
      "w": 5
    },
    {
      "char": "X",
      "x": 118,
      "y": 0,
      "w": 5
    },
    {
      "char": "Y",
      "x": 124,
      "y": 0,
      "w": 5
    },
    {
      "char": "Z",
      "x": 130,
      "y": 0,
      "w": 5
    },
    {
      "char": "a",
      "x": 136,
      "y": 0,
      "w": 4
    },
    {
      "char": "b",
      "x": 141,
      "y": 0,
      "w": 4
    },
    {
      "char": "c",
      "x": 146,
      "y": 0,
      "w": 4
    },
    {
      "char": "d",
      "x": 151,
      "y": 0,
      "w": 4
    },
    {
      "char": "e",
      "x": 156,
      "y": 0,
      "w": 4
    },
    {
      "char": "f",
      "x": 161,
      "y": 0,
      "w": 4
    },
    {
      "char": "g",
      "x": 166,
      "y": 0,
      "w": 4
    },
    {
      "char": "h",
      "x": 171,
      "y": 0,
      "w": 4
    },
    {
      "char": "i",
      "x": 176,
      "y": 0,
      "w": 1
    },
    {
      "char": "j",
      "x": 178,
      "y": 0,
      "w": 4
    },
    {
      "char": "k",
      "x": 183,
      "y": 0,
      "w": 4
    },
    {
      "char": "l",
      "x": 188,
      "y": 0,
      "w": 1
    },
    {
      "char": "m",
      "x": 190,
      "y": 0,
      "w": 5
    },
    {
      "char": "n",
      "x": 196,
      "y": 0,
      "w": 4
    },
    {
      "char": "o",
      "x": 201,
      "y": 0,
      "w": 4
    },
    {
      "char": "p",
      "x": 206,
      "y": 0,
      "w": 4
    },
    {
      "char": "q",
      "x": 211,
      "y": 0,
      "w": 4
    },
    {
      "char": "r",
      "x": 216,
      "y": 0,
      "w": 4
    },
    {
      "char": "s",
      "x": 221,
      "y": 0,
      "w": 4
    },
    {
      "char": "t",
      "x": 226,
      "y": 0,
      "w": 3
    },
    {
      "char": "u",
      "x": 230,
      "y": 0,
      "w": 4
    },
    {
      "char": "v",
      "x": 235,
      "y": 0,
      "w": 5
    },
    {
      "char": "w",
      "x": 241,
      "y": 0,
      "w": 5
    },
    {
      "char": "x",
      "x": 247,
      "y": 0,
      "w": 5
    },
    {
      "char": "y",
      "x": 253,
      "y": 0,
      "w": 5
    },
    {
      "char": "z",
      "x": 259,
      "y": 0,
      "w": 4
    },
    {
      "char": "1",
      "x": 0,
      "y": 7,
      "w": 3
    },
    {
      "char": "2",
      "x": 4,
      "y": 7,
      "w": 4
    },
    {
      "char": "3",
      "x": 9,
      "y": 7,
      "w": 4
    },
    {
      "char": "4",
      "x": 14,
      "y": 7,
      "w": 4
    },
    {
      "char": "5",
      "x": 19,
      "y": 7,
      "w": 4
    },
    {
      "char": "6",
      "x": 24,
      "y": 7,
      "w": 4
    },
    {
      "char": "7",
      "x": 29,
      "y": 7,
      "w": 4
    },
    {
      "char": "8",
      "x": 34,
      "y": 7,
      "w": 4
    },
    {
      "char": "9",
      "x": 39,
      "y": 7,
      "w": 4
    },
    {
      "char": "0",
      "x": 44,
      "y": 7,
      "w": 4
    },
    {
      "char": " ",
      "x": 49,
      "y": 7,
      "w": 3
    },
    {
      "char": "!",
      "x": 53,
      "y": 7,
      "w": 1
    },
    {
      "char": "@",
      "x": 55,
      "y": 7,
      "w": 5
    },
    {
      "char": "#",
      "x": 61,
      "y": 7,
      "w": 5
    },
    {
      "char": "$",
      "x": 67,
      "y": 7,
      "w": 5
    },
    {
      "char": "%",
      "x": 73,
      "y": 7,
      "w": 5
    },
    {
      "char": "^",
      "x": 79,
      "y": 7,
      "w": 5
    },
    {
      "char": "&",
      "x": 85,
      "y": 7,
      "w": 5
    },
    {
      "char": "*",
      "x": 91,
      "y": 7,
      "w": 5
    },
    {
      "char": "(",
      "x": 97,
      "y": 7,
      "w": 3
    },
    {
      "char": ")",
      "x": 101,
      "y": 7,
      "w": 3
    },
    {
      "char": "-",
      "x": 105,
      "y": 7,
      "w": 3
    },
    {
      "char": "_",
      "x": 109,
      "y": 7,
      "w": 4
    },
    {
      "char": "=",
      "x": 114,
      "y": 7,
      "w": 4
    },
    {
      "char": "+",
      "x": 119,
      "y": 7,
      "w": 5
    },
    {
      "char": "[",
      "x": 125,
      "y": 7,
      "w": 5
    },
    {
      "char": "{",
      "x": 131,
      "y": 7,
      "w": 5
    },
    {
      "char": "]",
      "x": 137,
      "y": 7,
      "w": 5
    },
    {
      "char": "}",
      "x": 143,
      "y": 7,
      "w": 5
    },
    {
      "char": "\\",
      "x": 149,
      "y": 7,
      "w": 5
    },
    {
      "char": "|",
      "x": 155,
      "y": 7,
      "w": 5
    },
    {
      "char": ";",
      "x": 161,
      "y": 7,
      "w": 2
    },
    {
      "char": ":",
      "x": 164,
      "y": 7,
      "w": 1
    },
    {
      "char": "'",
      "x": 166,
      "y": 7,
      "w": 1
    },
    {
      "char": "\"",
      "x": 168,
      "y": 7,
      "w": 5
    },
    {
      "char": ",",
      "x": 174,
      "y": 7,
      "w": 2
    },
    {
      "char": "<",
      "x": 177,
      "y": 7,
      "w": 4
    },
    {
      "char": ".",
      "x": 182,
      "y": 7,
      "w": 2
    },
    {
      "char": ">",
      "x": 185,
      "y": 7,
      "w": 4
    },
    {
      "char": "/",
      "x": 190,
      "y": 7,
      "w": 5
    },
    {
      "char": "?",
      "x": 196,
      "y": 7,
      "w": 5
    },
    {
      "char": "`",
      "x": 202,
      "y": 7,
      "w": 5
    },
    {
      "char": "~",
      "x": 208,
      "y": 7,
      "w": 5
    }
  ]
}